alpy/__init__.py
alpy/config.py
alpy/console.py
alpy/container.py
alpy/node.py
alpy/pexpect_log.py
alpy/qemu.py
alpy/remote_shell.py
alpy/run.py
alpy/utils.py
alpy-5.0.0.dist-info/licenses/LICENSE
alpy-5.0.0.dist-info/METADATA
alpy-5.0.0.dist-info/WHEEL
alpy-5.0.0.dist-info/top_level.txt
alpy-5.0.0.dist-info/RECORD
