Metadata-Version: 2.4
Name: alpy
Version: 5.0.0
Summary: Library for testing network virtual appliances using Docker
Author-email: Alexey Bogdanenko <alexey@bogdanenko.com>
Project-URL: Changelog, https://gitlab.com/abogdanenko/alpy/-/blob/main/CHANGELOG.md
Project-URL: Homepage, https://gitlab.com/abogdanenko/alpy
Classifier: Development Status :: 5 - Production/Stable
Classifier: Environment :: Console
Classifier: Intended Audience :: Developers
Classifier: License :: OSI Approved :: GNU General Public License v3 or later (GPLv3+)
Classifier: Operating System :: POSIX :: Linux
Classifier: Programming Language :: Python :: 3
Classifier: Programming Language :: Python :: 3.8
Classifier: Programming Language :: Python :: 3.9
Classifier: Programming Language :: Python :: 3.10
Classifier: Programming Language :: Python :: 3.11
Classifier: Programming Language :: Python :: 3.12
Classifier: Programming Language :: Python :: 3.13
Classifier: Programming Language :: Python :: 3 :: Only
Classifier: Topic :: Software Development :: Quality Assurance
Classifier: Topic :: Software Development :: Testing
Requires-Python: >=3.8
License-File: LICENSE
Requires-Dist: docker
Requires-Dist: pexpect
Requires-Dist: qmp
Dynamic: license-file
